<?xml version="1.0" encoding="iso-8859-1" standalone="no"?>
<!-- <?xml version="1.0" encoding="UTF-8"?> -->
<!DOCTYPE agenda>
stana

<agenda>
    <contacto>
        <nombre>Pepe</nombre>
        <apellidos>Gonzalez</apellidos>
        <direccion>Calle falsa, casa 1</direccion>
        <telefonos>
            <casa>95487651</casa>
            <trabajo>984654984</trabajo>
            <movil>65198765</movil>
        </telefonos>
    </contacto>
    <contacto>
        <nombre>Raul</nombre>
        <apellidos>Sebastian</apellidos>
        <direccion>Calle falsa 2, casa 1</direccion>
        <telefonos>
            <casa>9846544</casa>
            <trabajo>984651357</trabajo>
            <movil>6513279</movil>
        </telefonos>
    </contacto>
    <contacto>
        <nombre>María</nombre>
        <apellidos>Hernandez</apellidos>
        <direccion>Calle falsa 3, casa 2</direccion>
        <telefonos>
            <casa>98765498765</casa>
            <trabajo>6519687654</trabajo>
            <movil>654987651</movil>
        </telefonos>
    </contacto>
    <contacto>
        <nombre>Cristina</nombre>
        <apellidos>Martinez</apellidos>
        <direccion>Calle falsa 4, casa 3</direccion>
        <telefonos>
            <casa>98765133564</casa>
            <trabajo>987987987</trabajo>
            <movil>654654654</movil>
        </telefonos>
    </contacto>
</agenda>